CHANGES.rst
LICENSE.txt
MANIFEST.in
README.rst
setup.py
pynt_contrib.egg-info/PKG-INFO
pynt_contrib.egg-info/SOURCES.txt
pynt_contrib.egg-info/dependency_links.txt
pynt_contrib.egg-info/requires.txt
pynt_contrib.egg-info/top_level.txt
pyntcontrib/__init__.py