Metadata-Version: 1.0
Name: pynt-contrib
Version: 0.2.0
Summary: Common pynt tasks.
Home-page: http://rags.github.com/pynt-contrib/
Author: Raghunandan Rao
Author-email: r.raghunandan@gmail.com
License: MIT License
Platform: UNKNOWN
